pvfalcondemo/LICENSE
pvfalcondemo/falcon_demo_file.py
pvfalcondemo/falcon_demo_mic.py
pvfalcondemo-2.0.0.dist-info/METADATA
pvfalcondemo-2.0.0.dist-info/WHEEL
pvfalcondemo-2.0.0.dist-info/entry_points.txt
pvfalcondemo-2.0.0.dist-info/top_level.txt
pvfalcondemo-2.0.0.dist-info/RECORD
