Metadata-Version: 2.1
Name: pvfalcondemo
Version: 2.0.0
Summary: Falcon Speaker Diarization engine demos
Home-page: https://github.com/Picovoice/falcon
Author: Picovoice
Author-email: hello@picovoice.ai
Keywords: Speaker Diarization,Speaker Identification,Voice Identification
Classifier: Development Status :: 5 - Production/Stable
Classifier: Intended Audience :: Developers
Classifier: License :: OSI Approved :: Apache Software License
Classifier: Operating System :: OS Independent
Classifier: Programming Language :: Python :: 3
Classifier: Topic :: Multimedia :: Sound/Audio :: Speech
Requires-Python: >=3.9
Requires-Dist: pvfalcon (==2.0.0)
Requires-Dist: pvrecorder (==1.2.4)
Requires-Dist: tabulate (==0.9.0)
